LICENSE
README.md
setup.py
aiograpi/__init__.py
aiograpi/config.py
aiograpi/exceptions.py
aiograpi/extractors.py
aiograpi/reqwests.py
aiograpi/story.py
aiograpi/types.py
aiograpi/utils.py
aiograpi/zones.py
aiograpi.egg-info/PKG-INFO
aiograpi.egg-info/SOURCES.txt
aiograpi.egg-info/dependency_links.txt
aiograpi.egg-info/requires.txt
aiograpi.egg-info/top_level.txt
aiograpi/mixins/__init__.py
aiograpi/mixins/account.py
aiograpi/mixins/album.py
aiograpi/mixins/auth.py
aiograpi/mixins/bloks.py
aiograpi/mixins/challenge.py
aiograpi/mixins/clip.py
aiograpi/mixins/collection.py
aiograpi/mixins/comment.py
aiograpi/mixins/direct.py
aiograpi/mixins/fbsearch.py
aiograpi/mixins/graphql.py
aiograpi/mixins/hashtag.py
aiograpi/mixins/highlight.py
aiograpi/mixins/igtv.py
aiograpi/mixins/insights.py
aiograpi/mixins/location.py
aiograpi/mixins/media.py
aiograpi/mixins/multiple_accounts.py
aiograpi/mixins/note.py
aiograpi/mixins/notification.py
aiograpi/mixins/password.py
aiograpi/mixins/photo.py
aiograpi/mixins/private.py
aiograpi/mixins/public.py
aiograpi/mixins/share.py
aiograpi/mixins/signup.py
aiograpi/mixins/story.py
aiograpi/mixins/timeline.py
aiograpi/mixins/totp.py
aiograpi/mixins/track.py
aiograpi/mixins/user.py
aiograpi/mixins/video.py