Metadata-Version: 2.2
Name: aiograpi
Version: 0.0.4
Summary: Asynchronous Instagram Private API wrapper
Home-page: https://github.com/subzeroid/aiograpi
Author: Mr.Robot
Author-email: mr.robot@example.org
License: MIT
Keywords: instagram private api,instagram-private-api,instagram api,instagram-api,instagram,instagram-scraper,instagram-client,instagram-stories,instagram-feed,instagram-reels,instagram-insights,downloader,uploader,videos,photos,albums,igtv,reels,stories,pictures,instagram-user-photos,instagram-photos,instagram-metadata,instagram-downloader,instagram-uploader,instagram-note
Classifier: Development Status :: 4 - Beta
Classifier: Intended Audience :: Developers
Classifier: License :: OSI Approved :: MIT License
Classifier: Topic :: Software Development :: Libraries :: Python Modules
Classifier: Programming Language :: Python :: 3.10
Classifier: Programming Language :: Python :: 3.11
Requires-Python: >=3.10
License-File: LICENSE
Requires-Dist: httpx==0.28.1
Requires-Dist: orjson==3.10.18
Requires-Dist: pydantic==2.11.5
Requires-Dist: moviepy==1.0.3
Requires-Dist: pycryptodomex==3.23.0
Requires-Dist: zstandard==0.23.0
Dynamic: author
Dynamic: author-email
Dynamic: classifier
Dynamic: description
Dynamic: description-content-type
Dynamic: home-page
Dynamic: keywords
Dynamic: license
Dynamic: requires-dist
Dynamic: requires-python
Dynamic: summary
